LICENSE
MANIFEST.in
README.md
setup.py
sanitize_ml_labels/__init__.py
sanitize_ml_labels/__version__.py
sanitize_ml_labels/absolutely_normalized_metrics.json
sanitize_ml_labels/descriptors.json
sanitize_ml_labels/find_true_hyphenated_words.py
sanitize_ml_labels/generic_words_cooccurring_with_descriptors.json
sanitize_ml_labels/hyphenated_words_index.json.gz
sanitize_ml_labels/is_normalized_metric.py
sanitize_ml_labels/labels.json
sanitize_ml_labels/normalized_metrics.json
sanitize_ml_labels/py.typed
sanitize_ml_labels/sanitize_ml_labels.py
sanitize_ml_labels/should_be_maximized.json
sanitize_ml_labels/should_be_maximized.py
sanitize_ml_labels/should_be_minimized.json
sanitize_ml_labels.egg-info/PKG-INFO
sanitize_ml_labels.egg-info/SOURCES.txt
sanitize_ml_labels.egg-info/dependency_links.txt
sanitize_ml_labels.egg-info/requires.txt
sanitize_ml_labels.egg-info/top_level.txt
tests/test_duplicates.py
tests/test_is_absolutely_normalized_metric.py
tests/test_is_normalized_metric.py
tests/test_readme.py
tests/test_sanitize_ml_labels.py
tests/test_should_be_maximized.py
tests/test_version.py