Metadata-Version: 2.1
Name: sanitize_ml_labels
Version: 1.1.5
Summary: Python package to sanitize in a standard way ML-related labels.
Home-page: https://github.com/LucaCappelletti94/sanitize_ml_labels
Author: Luca Cappelletti,Tommaso Fontana
Author-email: cappelletti.luca94@gmail.com,tommaso.fontana.96@gmail.com
License: MIT
Classifier: Development Status :: 5 - Production/Stable
Classifier: License :: OSI Approved :: MIT License
Classifier: Programming Language :: Python :: 3
License-File: LICENSE
Requires-Dist: compress-json
Provides-Extra: test
Requires-Dist: pytest; extra == "test"
Requires-Dist: pytest-readme; extra == "test"
Requires-Dist: validate_version_code; extra == "test"
